aicommit/__init__.py
aicommit/cli/__init__.py
aicommit/cli/main.py
aicommit/models/__init__.py
aicommit/models/base.py
aicommit/models/config.py
aicommit/models/deepseek.py
aicommit/models/openai.py
aicommit/models/prompts.py
aicommit/models/qwen.py
aicommit/utils/__init__.py
aicommit/utils/git.py
aicommit_simongino-0.1.0.dist-info/METADATA
aicommit_simongino-0.1.0.dist-info/WHEEL
aicommit_simongino-0.1.0.dist-info/entry_points.txt
aicommit_simongino-0.1.0.dist-info/RECORD
