Metadata-Version: 2.4
Name: aicommit-simongino
Version: 0.1.0
Summary: AI-powered git commit message generator
License-Expression: MIT
Requires-Python: <3.13,>=3.10
Requires-Dist: typer>=0.9.0
Requires-Dist: rich>=13.7.0
Requires-Dist: pydantic>=2.0.0
Requires-Dist: dashscope>=1.13.6
Requires-Dist: gitpython>=3.1.40
Requires-Dist: tomlkit>=0.12.0
Requires-Dist: openai>=1.61.1
Requires-Dist: tomli>=2.0.1; python_version < "3.11"
Requires-Dist: twine>=6.1.0
